juice_core/SHTRestInterface.py
juice_core/__init__.py
juice_core_uplink_api_client/__init__.py
juice_core_uplink_api_client/api/__init__.py
juice_core_uplink_api_client/api/api_token_auth/__init__.py
juice_core_uplink_api_client/api/api_token_auth/post_api_token_auth.py
juice_core_uplink_api_client/api/api_token_refresh/__init__.py
juice_core_uplink_api_client/api/api_token_refresh/post_api_token_refresh.py
juice_core_uplink_api_client/api/rest_api/__init__.py
juice_core_uplink_api_client/api/rest_api/delete_plan_by_id.py
juice_core_uplink_api_client/api/rest_api/delete_plan_by_id_and_format.py
juice_core_uplink_api_client/api/rest_api/get_checks.py
juice_core_uplink_api_client/api/rest_api/get_checks_by_format.py
juice_core_uplink_api_client/api/rest_api/get_checks_by_working_group_mnemonic.py
juice_core_uplink_api_client/api/rest_api/get_checks_by_working_group_mnemonic_and_format.py
juice_core_uplink_api_client/api/rest_api/get_config.py
juice_core_uplink_api_client/api/rest_api/get_config_by_format.py
juice_core_uplink_api_client/api/rest_api/get_detailed_scenario.py
juice_core_uplink_api_client/api/rest_api/get_detailed_scenario_by_format.py
juice_core_uplink_api_client/api/rest_api/get_detailed_scenario_by_id.py
juice_core_uplink_api_client/api/rest_api/get_detailed_scenario_by_id_and_format.py
juice_core_uplink_api_client/api/rest_api/get_events.py
juice_core_uplink_api_client/api/rest_api/get_events_by_format.py
juice_core_uplink_api_client/api/rest_api/get_fdyn_event.py
juice_core_uplink_api_client/api/rest_api/get_fdyn_event_by_format.py
juice_core_uplink_api_client/api/rest_api/get_fdyn_event_definition.py
juice_core_uplink_api_client/api/rest_api/get_fdyn_event_definition_by_format.py
juice_core_uplink_api_client/api/rest_api/get_fdyn_event_file.py
juice_core_uplink_api_client/api/rest_api/get_fdyn_event_file_by_format.py
juice_core_uplink_api_client/api/rest_api/get_file_by_filename.py
juice_core_uplink_api_client-0.2.12.dist-info/LICENSE
juice_core_uplink_api_client-0.2.12.dist-info/METADATA
juice_core_uplink_api_client-0.2.12.dist-info/WHEEL
juice_core_uplink_api_client-0.2.12.dist-info/RECORD
