Metadata-Version: 2.1
Name: juice-core-uplink-api-client
Version: 0.2.12
Summary: A client library for accessing Juice Core Uplink API
Home-page: https://JANUS-JUICE.github.io/juice-core-uplink-api-client
License: MIT
Author: Luca Penasa
Author-email: luca.penasa@inaf.it
Requires-Python: >=3.10,<4.0
Classifier: Development Status :: 4 - Beta
Classifier: Intended Audience :: Developers
Classifier: License :: OSI Approved :: MIT License
Classifier: Operating System :: OS Independent
Classifier: Programming Language :: Python
Classifier: Programming Language :: Python :: 3
Classifier: Programming Language :: Python :: 3.10
Classifier: Programming Language :: Python :: 3.11
Classifier: Programming Language :: Python :: 3.12
Classifier: Topic :: Software Development :: Libraries :: Python Modules
Classifier: Typing :: Typed
Requires-Dist: attrs (>=24.2.0,<25.0.0)
Requires-Dist: httpx (>=0.27.2,<0.28.0)
Requires-Dist: importlib-metadata (>=8.5.0,<9.0.0)
Requires-Dist: loguru (>=0.7.2,<0.8.0)
Requires-Dist: merge-args (>=0.1.5,<0.2.0)
Requires-Dist: pandas (>=2.2.3,<3.0.0)
Requires-Dist: python-dateutil (>=2.9.0.post0,<3.0.0)
Project-URL: Documentation, https://JANUS-JUICE.github.io/juice-core-uplink-api-client
Project-URL: Repository, https://github.com/JANUS-JUICE/juice-core-uplink-api-client
